pipedown/__init__.py
pipedown/cross_validation/__init__.py
pipedown/cross_validation/implementations/__init__.py
pipedown/cross_validation/implementations/cross_validation_implementation.py
pipedown/cross_validation/implementations/sequential.py
pipedown/cross_validation/splitters/__init__.py
pipedown/cross_validation/splitters/cross_validation_splitter.py
pipedown/cross_validation/splitters/out_of_time_splitter.py
pipedown/cross_validation/splitters/random_splitter.py
pipedown/cross_validation/splitters/stratified_splitter.py
pipedown/cross_validation/splitters/time_bin_splitter.py
pipedown/dag/__init__.py
pipedown/dag/dag.py
pipedown/dag/dag_tools.py
pipedown/dag/io.py
pipedown/nodes/__init__.py
pipedown/nodes/base/__init__.py
pipedown/nodes/base/cache.py
pipedown/nodes/base/input.py
pipedown/nodes/base/loader.py
pipedown/nodes/base/metric.py
pipedown/nodes/base/model.py
pipedown/nodes/base/node.py
pipedown/nodes/base/primary.py
pipedown/nodes/caches/__init__.py
pipedown/nodes/caches/feather_cache.py
pipedown/nodes/caches/in_memory_cache.py
pipedown/nodes/caches/pickle_cache.py
pipedown/nodes/filters/__init__.py
pipedown/nodes/filters/collate.py
pipedown/nodes/filters/feature_filter.py
pipedown/nodes/filters/item_filter.py
pipedown/nodes/loaders/__init__.py
pipedown/nodes/loaders/csv_loader.py
pipedown/nodes/loaders/pymongo_loader.py
pipedown/nodes/loaders/sqlalchemy_loader.py
pipedown/nodes/metrics/__init__.py
pipedown/nodes/metrics/mean_absolute_percentage_error.py
pipedown/nodes/metrics/mean_squared_error.py
pipedown/nodes/metrics/median_absolute_percentage_error.py
pipedown/nodes/models/__init__.py
pipedown/nodes/models/catboost_regressor_model.py
pipedown/nodes/models/log_transformed_model.py
pipedown/nodes/transforms/__init__.py
pipedown/nodes/transforms/imputer.py
pipedown/nodes/transforms/min_max_scaler.py
pipedown/nodes/transforms/null_fallback.py
pipedown/nodes/transforms/one_hot_encoder.py
pipedown/nodes/transforms/rename_fields.py
pipedown-0.1.0.dist-info/LICENSE
pipedown-0.1.0.dist-info/METADATA
pipedown-0.1.0.dist-info/WHEEL
pipedown-0.1.0.dist-info/top_level.txt
pipedown-0.1.0.dist-info/RECORD
