Metadata-Version: 2.1
Name: pipedown
Version: 0.1.0
Summary: A data science pipelining framework for Python
Home-page: https://github.com/brendanhasz/pipedown
Author: Brendan Hasz
Author-email: winsto99@gmail.com
License: MIT
Platform: UNKNOWN
Classifier: Programming Language :: Python :: 3
Classifier: License :: OSI Approved :: MIT License
Classifier: Operating System :: OS Independent
Classifier: Development Status :: 3 - Alpha
Requires-Dist: cloudpickle (>=1.6.0)
Requires-Dist: graphviz (>=0.16)
Requires-Dist: Jinja2 (>=2.0.0)
Requires-Dist: markdown (>=3.3.0)
Requires-Dist: matplotlib (>=3.0.0)
Requires-Dist: numpy (>=1.10.0)
Requires-Dist: pandas (>=1.0.0)
Provides-Extra: dev
Requires-Dist: autoflake (>=1.4) ; extra == 'dev'
Requires-Dist: black (>=19.10b0) ; extra == 'dev'
Requires-Dist: bumpversion (>=0.6.0) ; extra == 'dev'
Requires-Dist: flake8 (>=3.8.3) ; extra == 'dev'
Requires-Dist: isort (>=5.1.2) ; extra == 'dev'
Requires-Dist: pytest (>=6.0.0rc1) ; extra == 'dev'
Requires-Dist: pytest-cov (>=2.7.1) ; extra == 'dev'
Requires-Dist: sphinx (>=3.1.2) ; extra == 'dev'
Requires-Dist: sphinx-rtd-theme (>=0.5.0) ; extra == 'dev'
Requires-Dist: setuptools (>=49.1.0) ; extra == 'dev'
Requires-Dist: twine (>=3.2.0) ; extra == 'dev'
Requires-Dist: wheel (>=0.34.2) ; extra == 'dev'
Requires-Dist: catboost ; extra == 'dev'
Requires-Dist: pyarrow ; extra == 'dev'
